metacopier_api/__init__.py
metacopier_api/api_client.py
metacopier_api/api_response.py
metacopier_api/configuration.py
metacopier_api/exceptions.py
metacopier_api/py.typed
metacopier_api/rest.py
metacopier_api/api/__init__.py
metacopier_api/api/account_api_api.py
metacopier_api/api/project_api_api.py
metacopier_api/api/trading_api_api.py
metacopier_api/api/type_api_api.py
metacopier_api/models/__init__.py
metacopier_api/models/account_dto.py
metacopier_api/models/account_information_dto.py
metacopier_api/models/account_status_dto.py
metacopier_api/models/account_type_dto.py
metacopier_api/models/copier_dto.py
metacopier_api/models/currency_type_dto.py
metacopier_api/models/feature_copier_filter_dto.py
metacopier_api/models/feature_dto.py
metacopier_api/models/feature_keep_alive_trade_dto.py
metacopier_api/models/feature_permitted_symbols_dto.py
metacopier_api/models/feature_setting_dto.py
metacopier_api/models/feature_telegram_notification_dto.py
metacopier_api/models/feature_type_dto.py
metacopier_api/models/invoice_dto.py
metacopier_api/models/log_dto.py
metacopier_api/models/log_type_dto.py
metacopier_api/models/payment_method_dto.py
metacopier_api/models/position_dto.py
metacopier_api/models/position_request_dto.py
metacopier_api/models/project_dto.py
metacopier_api/models/region_dto.py
metacopier_api/models/risk_limit_dto.py
metacopier_api/models/risk_limit_status_dto.py
metacopier_api/models/risk_type_dto.py
metacopier_api/models/scale_type_dto.py
metacopier_api/models/strategy_dto.py
metacopier_api/models/symbol_mapping_dto.py
metacopier_api/models/telegram_notification_dto.py
metacopier_api-0.9.1.dist-info/LICENSE
metacopier_api-0.9.1.dist-info/METADATA
metacopier_api-0.9.1.dist-info/WHEEL
metacopier_api-0.9.1.dist-info/top_level.txt
metacopier_api-0.9.1.dist-info/RECORD
